datacatalog_fileset_processor/__init__.py
datacatalog_fileset_processor/constant.py
datacatalog_fileset_processor/datacatalog_entity_factory.py
datacatalog_fileset_processor/datacatalog_facade.py
datacatalog_fileset_processor/datacatalog_fileset_processor_cli.py
datacatalog_fileset_processor/fileset_datasource_processor.py
datacatalog_fileset_processor/values_comparable_object.py
datacatalog_fileset_processor-0.1.5.dist-info/AUTHORS.rst
datacatalog_fileset_processor-0.1.5.dist-info/LICENSE
datacatalog_fileset_processor-0.1.5.dist-info/METADATA
datacatalog_fileset_processor-0.1.5.dist-info/WHEEL
datacatalog_fileset_processor-0.1.5.dist-info/entry_points.txt
datacatalog_fileset_processor-0.1.5.dist-info/top_level.txt
datacatalog_fileset_processor-0.1.5.dist-info/RECORD
